calibpipe/__init__.py
calibpipe/_version.py
calibpipe/version.py
calibpipe/_dev_version/__init__.py
calibpipe/atmosphere/__init__.py
calibpipe/atmosphere/atmosphere_containers.py
calibpipe/atmosphere/meteo_data_handlers.py
calibpipe/atmosphere/models/README.md
calibpipe/atmosphere/models/__init__.py
calibpipe/atmosphere/models/macobac.ecsv
calibpipe/atmosphere/models/reference_MDPs/__init__.py
calibpipe/atmosphere/models/reference_MDPs/ref_density_at_15km_ctao-north_intermediate.ecsv
calibpipe/atmosphere/models/reference_MDPs/ref_density_at_15km_ctao-north_summer.ecsv
calibpipe/atmosphere/models/reference_MDPs/ref_density_at_15km_ctao-north_winter.ecsv
calibpipe/atmosphere/models/reference_MDPs/ref_density_at_15km_ctao-south_summer.ecsv
calibpipe/atmosphere/models/reference_MDPs/ref_density_at_15km_ctao-south_winter.ecsv
calibpipe/atmosphere/models/reference_atmospheres/__init__.py
calibpipe/atmosphere/models/reference_atmospheres/reference_atmo_model_v0_ctao-north_intermediate.ecsv
calibpipe/atmosphere/models/reference_atmospheres/reference_atmo_model_v0_ctao-north_summer.ecsv
calibpipe/atmosphere/models/reference_atmospheres/reference_atmo_model_v0_ctao-north_winter.ecsv
calibpipe/atmosphere/models/reference_atmospheres/reference_atmo_model_v0_ctao-south_summer.ecsv
calibpipe/atmosphere/models/reference_atmospheres/reference_atmo_model_v0_ctao-south_winter.ecsv
calibpipe/atmosphere/models/reference_rayleigh_scattering_profiles/__init__.py
calibpipe/atmosphere/models/reference_rayleigh_scattering_profiles/reference_rayleigh_extinction_profile_v0_ctao-north_intermediate.ecsv
calibpipe/atmosphere/models/reference_rayleigh_scattering_profiles/reference_rayleigh_extinction_profile_v0_ctao-north_summer.ecsv
calibpipe/atmosphere/models/reference_rayleigh_scattering_profiles/reference_rayleigh_extinction_profile_v0_ctao-north_winter.ecsv
calibpipe/atmosphere/models/reference_rayleigh_scattering_profiles/reference_rayleigh_extinction_profile_v0_ctao-south_summer.ecsv
ctao_calibpipe-0.4.0.dist-info/licenses/AUTHORS.md
ctao_calibpipe-0.4.0.dist-info/licenses/LICENSE
ctao_calibpipe-0.4.0.dist-info/METADATA
ctao_calibpipe-0.4.0.dist-info/WHEEL
ctao_calibpipe-0.4.0.dist-info/entry_points.txt
ctao_calibpipe-0.4.0.dist-info/top_level.txt
ctao_calibpipe-0.4.0.dist-info/RECORD
