Metadata-Version: 2.4
Name: ctao-calibpipe
Version: 0.4.0
Author: Leonid Burmistrov, Mykhailo Dalchenko, Antonio Di Pilato, Gabriel Emery, Tjark Miener, Gregoire Uhlrich, Georgios Voutsinas, Vadym Voitsekhovskyi
Classifier: License :: OSI Approved :: MIT License
Requires-Python: >=3.10
License-File: LICENSE
License-File: AUTHORS.md
Requires-Dist: astral
Requires-Dist: astropy
Requires-Dist: cdsapi
Requires-Dist: ctapipe[all]>=0.29.0
Requires-Dist: ctapipe-io-zfits>=0.4.1
Requires-Dist: h5py
Requires-Dist: iminuit
Requires-Dist: molecularprofiles>=3.0.0
Requires-Dist: numpy
Requires-Dist: pandas
Requires-Dist: psycopg[binary]
Requires-Dist: pygrib
Requires-Dist: pyrdams>=3.0.1
Requires-Dist: requests>=2.27
Requires-Dist: requests
Requires-Dist: sqlalchemy>=2.0.1
Requires-Dist: traitlets
Provides-Extra: test
Requires-Dist: black>=22.5; extra == "test"
Requires-Dist: coverage-badge; extra == "test"
Requires-Dist: cwltool; extra == "test"
Requires-Dist: nodejs-bin[cmd]; extra == "test"
Requires-Dist: pylint>=2.15; extra == "test"
Requires-Dist: pytest-cov; extra == "test"
Requires-Dist: pytest-order; extra == "test"
Requires-Dist: pytest; extra == "test"
Requires-Dist: pyyaml; extra == "test"
Requires-Dist: pytest-requirements; extra == "test"
Provides-Extra: doc
Requires-Dist: linkify-it-py; extra == "doc"
Requires-Dist: myst-parser; extra == "doc"
Requires-Dist: nbsphinx; extra == "doc"
Requires-Dist: numpydoc; extra == "doc"
Requires-Dist: ctao-sphinx-theme; extra == "doc"
Requires-Dist: cwltool; extra == "doc"
Requires-Dist: sphinx-argparse; extra == "doc"
Requires-Dist: sphinx-paramlinks; extra == "doc"
Requires-Dist: sphinx>=8.2.1; extra == "doc"
Requires-Dist: sphinx-changelog; extra == "doc"
Requires-Dist: nodejs-bin[cmd]; extra == "doc"
Requires-Dist: playwright; extra == "doc"
Provides-Extra: dev
Requires-Dist: setuptools_scm; extra == "dev"
Requires-Dist: towncrier; extra == "dev"
Requires-Dist: pre-commit; extra == "dev"
Provides-Extra: all
Requires-Dist: ctao-calibpipe[dev,doc,test]; extra == "all"
Dynamic: license-file
